ACKNOWLEDGEMENTS
CODE_OF_CONDUCT.md
LICENSE
MANIFEST.in
README.md
requirements.txt
requirements_dev.txt
run_install_nvm.sh
run_tests.sh
setup.cfg
setup.py
diplomacy/README_COMMANDS.txt
diplomacy/README_MAPS.txt
diplomacy/README_RULES.txt
diplomacy/__init__.py
diplomacy/settings.py
diplomacy/version.py
diplomacy/version.pyc
diplomacy.egg-info/PKG-INFO
diplomacy.egg-info/SOURCES.txt
diplomacy.egg-info/dependency_links.txt
diplomacy.egg-info/requires.txt
diplomacy.egg-info/top_level.txt
diplomacy/client/__init__.py
diplomacy/client/channel.py
diplomacy/client/connection.py
diplomacy/client/game_instances_set.py
diplomacy/client/network_game.py
diplomacy/client/notification_managers.py
diplomacy/client/response_managers.py
diplomacy/communication/__init__.py
diplomacy/communication/notifications.py
diplomacy/communication/requests.py
diplomacy/communication/responses.py
diplomacy/daide/__init__.py
diplomacy/daide/clauses.py
diplomacy/daide/connection_handler.py
diplomacy/daide/messages.py
diplomacy/daide/notification_managers.py
diplomacy/daide/notifications.py
diplomacy/daide/request_managers.py
diplomacy/daide/requests.py
diplomacy/daide/responses.py
diplomacy/daide/server.py
diplomacy/daide/tokens.py
diplomacy/daide/utils.py
diplomacy/daide/tests/__init__.py
diplomacy/daide/tests/game_data_1.csv
diplomacy/daide/tests/game_data_1_history.csv
diplomacy/daide/tests/game_data_1_reject_map.csv
diplomacy/daide/tests/game_data_7.csv
diplomacy/daide/tests/game_data_7_draw.csv
diplomacy/daide/tests/game_data_7_press.csv
diplomacy/daide/tests/test_daide_game.py
diplomacy/daide/tests/test_requests.py
diplomacy/daide/tests/test_responses.py
diplomacy/daide/tests/test_tokens.py
diplomacy/engine/__init__.py
diplomacy/engine/game.py
diplomacy/engine/map.py
diplomacy/engine/message.py
diplomacy/engine/power.py
diplomacy/engine/renderer.py
diplomacy/integration/__init__.py
diplomacy/integration/base_api.py
diplomacy/integration/webdiplomacy_net/__init__.py
diplomacy/integration/webdiplomacy_net/api.py
diplomacy/integration/webdiplomacy_net/game.py
diplomacy/integration/webdiplomacy_net/orders.py
diplomacy/integration/webdiplomacy_net/utils.py
