Metadata-Version: 2.1
Name: diplomacy
Version: 1.1.1
Summary: Diplomacy: DATC-Compliant Game Engine with Web Interface
Home-page: https://github.com/diplomacy/diplomacy
Author: Philip Paquette
Author-email: pcpaquette@gmail.com
License: UNKNOWN
Project-URL: Source, https://github.com/diplomacy/diplomacy/
Project-URL: Documentation, https://docs.diplomacy.ai/
Project-URL: Bug Reports, https://github.com/diplomacy/diplomacy/issues
Keywords: diplomacy diplomacy-game game negotiation
Platform: UNKNOWN
Classifier: License :: OSI Approved :: GNU Affero General Public License v3 or later (AGPLv3+)
Classifier: Programming Language :: Python :: 3
Classifier: Programming Language :: Python :: 3.5
Classifier: Programming Language :: Python :: 3.6
Classifier: Programming Language :: Python :: 3.7
Classifier: Topic :: Games/Entertainment :: Board Games
Requires-Python: >=3.5
